{
    "bundle": {
        "js/pages/group": {
            "scripts": [
                "userfrosting/js/widgets/users.js",
                "userfrosting/js/widgets/groups.js",
                "userfrosting/js/pages/group.js"
            ],
            "options": {
                "result": {
                    "type": {
                        "scripts": "plain"
                    }
                }
            }
        },
        "js/pages/permission": {
            "scripts": [
                "userfrosting/js/widgets/users.js",
                "userfrosting/js/pages/permission.js"
            ],
            "options": {
                "result": {
                    "type": {
                        "scripts": "plain"
                    }
                }
            }
        },
        "js/pages/role": {
            "scripts": [
                "userfrosting/js/widgets/users.js",
                "userfrosting/js/widgets/roles.js",
                "userfrosting/js/pages/role.js"
            ],
            "options": {
                "result": {
                    "type": {
                        "scripts": "plain"
                    }
                }
            }
        },
        "js/pages/permissions": {
            "scripts": [
                "userfrosting/js/pages/permissions.js"
            ],
            "options": {
                "result": {
                    "type": {
                        "scripts": "plain"
                    }
                }
            }
        }
    }
}
